Workbook

Sheet House Project Costs
A1: Contractor / Supplier | B1: Trade | C1: Quote 1 (£) | D1: Quote 2 (£) | E1: Total Quoted (£) | F1: Paid (£) | G1: Balance (£) | H1: Status | I1: Notes | K1: Running Totals
A2: Martin | B2: Builder | C2: 3100 | D2: 280 | E2: =SUM(C2:D2) | F2: 0 | G2: =E2-F2 | H2: Quoted | K2: Total Quoted | L2: =SUM(E2:E100)
A3: Jason | B3: Carpets | C3: 340 | E3: =SUM(C3:D3) | F3: 70 | G3: =E3-F3 | H3: Part paid | I3: Carpets already purchased | K3: Total Paid | L3: =SUM(F2:F100)
A4: Building Regulations | B4: Fees | C4: 650 | E4: =SUM(C4:D4) | F4: 0 | G4: =E4-F4 | H4: Outstanding | K4: Balance Remaining | L4: =L2-L3
A5: Ian | B5: Painter & Decorator | E5: =SUM(C5:D5) | F5: 0 | G5: =E5-F5 | H5: Awaiting quote | K5: Paid % | L5: =IF(L2=0,0,L3/L2)
A6: Brett | B6: Electrics | E6: =SUM(C6:D6) | F6: 0 | G6: =E6-F6 | H6: Awaiting quote | K6: Quotes Awaiting | L6: =COUNTIF(H2:H100,"Awaiting quote")
A7: Richard | B7: Woodwork | E7: =SUM(C7:D7) | F7: 0 | G7: =E7-F7 | H7: Awaiting quote
A8: Scott | B8: Plasterer | E8: =SUM(C8:D8) | F8: 0 | G8: =E8-F8 | H8: Awaiting quote
A9: Skip Hire | B9: Waste Removal | C9: 335 | E9: =SUM(C9:D9) | F9: 0 | G9: =E9-F9 | H9: Outstanding | I9: Pay driver on the day
E10: =SUM(C10:D10) | G10: =E10-F10
E11: =SUM(C11:D11) | G11: =E11-F11
E12: =SUM(C12:D12) | G12: =E12-F12
E13: =SUM(C13:D13) | G13: =E13-F13
E14: =SUM(C14:D14) | G14: =E14-F14
E15: =SUM(C15:D15) | G15: =E15-F15
E16: =SUM(C16:D16) | G16: =E16-F16
E17: =SUM(C17:D17) | G17: =E17-F17
E18: =SUM(C18:D18) | G18: =E18-F18
E19: =SUM(C19:D19) | G19: =E19-F19
E20: =SUM(C20:D20) | G20: =E20-F20
E21: =SUM(C21:D21) | G21: =E21-F21
... E100: =SUM(C100:D100) | G100: =E100-F100

Sheet Payments
A1: Date | B1: Contractor / Supplier | C1: Trade | D1: Description | E1: Amount Paid (£) | F1: Payment Method | G1: Invoice / Receipt | H1: Notes
B2: Jason | C2: Carpets | D2: Deposit / part payment | E2: 70

Sheet Materials
A1: Date | B1: Room / Area | C1: Item | D1: Supplier | E1: Quantity | F1: Unit Cost (£) | G1: Total Cost (£) | H1: Paid (£) | I1: Balance (£) | J1: Notes
G2: =IF(OR(E2="",F2=""),0,E2*F2) | I2: =G2-H2
G3: =IF(OR(E3="",F3=""),0,E3*F3) | I3: =G3-H3
G4: =IF(OR(E4="",F4=""),0,E4*F4) | I4: =G4-H4
G5: =IF(OR(E5="",F5=""),0,E5*F5) | I5: =G5-H5
G6: =IF(OR(E6="",F6=""),0,E6*F6) | I6: =G6-H6
G7: =IF(OR(E7="",F7=""),0,E7*F7) | I7: =G7-H7
G8: =IF(OR(E8="",F8=""),0,E8*F8) | I8: =G8-H8
G9: =IF(OR(E9="",F9=""),0,E9*F9) | I9: =G9-H9
G10: =IF(OR(E10="",F10=""),0,E10*F10) | I10: =G10-H10
G11: =IF(OR(E11="",F11=""),0,E11*F11) | I11: =G11-H11
G12: =IF(OR(E12="",F12=""),0,E12*F12) | I12: =G12-H12
G13: =IF(OR(E13="",F13=""),0,E13*F13) | I13: =G13-H13
... G200: =IF(OR(E200="",F200=""),0,E200*F200) | I200: =G200-H200

Sheet Dashboard
A1: House Project Dashboard
A4: Project Metric | B4: Current Total | D4: Status | E4: Count
A5: Total Quoted | B5: ='House Project Costs'!L2 | D5: Awaiting quote | E5: =COUNTIF('House Project Costs'!H2:H100,"Awaiting quote")
A6: Total Paid | B6: ='House Project Costs'!L3 | D6: Quoted | E6: =COUNTIF('House Project Costs'!H2:H100,"Quoted")
A7: Balance Remaining | B7: ='House Project Costs'!L4 | D7: Part paid | E7: =COUNTIF('House Project Costs'!H2:H100,"Part paid")
A8: Quotes Awaiting | B8: ='House Project Costs'!L6 | D8: Paid | E8: =COUNTIF('House Project Costs'!H2:H100,"Paid")
D9: Outstanding | E9: =COUNTIF('House Project Costs'!H2:H100,"Outstanding")
D10: Total entries | E10: =COUNTA('House Project Costs'!A2:A100)
